{"duration": 0.011688947677612305, "input_args": {"transformer": "StackingEstimator(estimator=LinearSVC(C=0.5, dual=False, penalty='l1'))", "X": "array([[ 1.        , -0.06963935,  0.11709477, ..., -0.08701227,\n         0.1376592 ,  0.0720308 ],\n       [ 1.        , -0.06963935,  0.11709477, ..., -0.08701227,\n         0.1376592 ,  0.0720308 ],\n       [ 1.        , -0.06963935,  0.11709477, ..., -0.08701227,\n         0.1376592 ,  0.0720308 ],\n       ...,\n       [ 0.0625    , -0.07064961,  0.14033695, ..., -0.13832086,\n         0.12763997, -0.02840679],\n       [ 0.07862903, -0.07063227,  0.14019058, ..., -0.13795708,\n         0.12833985, -0.02664877],\n       [ 0.0625    , -0.07064961,  0.14033695, ..., -0.13832086,\n         0.12763997, -0.02840679]])", "y": "0       1.0\n1       1.0\n2       1.0\n3       1.0\n4       1.0\n       ... \n1492    0.0\n1493    0.0\n1494    0.0\n1495    0.0\n1496    0.0\nName: complex, Length: 1198, dtype: float64", "weight": "None", "message_clsname": "'Pipeline'", "message": "None", "**": "{}"}}