{"duration": 0.23032283782958984, "input_args": {"transformer": "FastICA(tol=0.8500000000000001)", "X": "array([[ 1.        , -1.        ,  1.        , ..., -1.        ,\n        -0.89868573, -1.        ],\n       [ 1.        , -1.        ,  1.        , ..., -1.        ,\n        -0.89868573, -1.        ],\n       [ 1.        , -1.        ,  1.        , ..., -1.        ,\n        -0.89868573, -1.        ],\n       ...,\n       [-0.61783461, -0.54954438,  0.88076479, ..., -0.58142914,\n        -1.        ,  0.15738841],\n       [-0.58955947, -0.55786209,  0.88349418, ..., -0.59500968,\n        -0.9993417 ,  0.13632425],\n       [-0.61783461, -0.54954438,  0.88076479, ..., -0.58142914,\n        -1.        ,  0.15738841]])", "y": "0       1.0\n1       1.0\n2       1.0\n3       1.0\n4       1.0\n       ... \n1492    0.0\n1493    0.0\n1494    0.0\n1495    0.0\n1496    0.0\nName: complex, Length: 1198, dtype: float64", "weight": "None", "message_clsname": "'Pipeline'", "message": "None", "**": "{}"}}