{"duration": 0.00642704963684082, "input_args": {"transformer": "StackingEstimator(estimator=DecisionTreeClassifier(criterion='entropy',\n                                                   max_depth=4,\n                                                   min_samples_leaf=19,\n                                                   min_samples_split=5))", "X": "array([[ 1.18887814, -0.02410067],\n       [ 1.18887814, -0.02410067],\n       [ 1.18887814, -0.02410067],\n       ...,\n       [-0.17031824,  0.07551879],\n       [-0.16854059,  0.0732924 ],\n       [-0.17031824,  0.07551879]])", "y": "0       1.0\n1       1.0\n2       1.0\n3       1.0\n4       1.0\n       ... \n1219    0.0\n1220    0.0\n1221    0.0\n1222    0.0\n1223    0.0\nName: complex, Length: 1198, dtype: float64", "weight": "None", "message_clsname": "'Pipeline'", "message": "None", "**": "{}"}}