{"duration": 0.06046009063720703, "input_args": {"transformer": "StackingEstimator(estimator=ExtraTreesClassifier(max_features=0.15000000000000002,\n                                                 min_samples_leaf=18,\n                                                 min_samples_split=11))", "X": "array([[-0.00286189, -0.01033615, -0.0147912 , ...,  0.08003903,\n         0.02900396,  0.08003903],\n       [-0.00286189, -0.01033615, -0.0147912 , ...,  0.08003903,\n         0.02900396,  0.08003903],\n       [-0.00286189, -0.01033615, -0.0147912 , ...,  0.08003903,\n         0.02900396,  0.08003903],\n       ...,\n       [ 0.37256209,  0.17484219,  0.2928552 , ...,  0.0365175 ,\n         0.51540995,  0.0365175 ],\n       [ 0.3696466 ,  0.17654914,  0.29215049, ...,  0.03985076,\n         0.5029089 ,  0.03985076],\n       [ 0.37256209,  0.17484219,  0.2928552 , ...,  0.0365175 ,\n         0.51540995,  0.0365175 ]])", "y": "0       1.0\n1       1.0\n2       1.0\n3       1.0\n4       1.0\n       ... \n1219    0.0\n1220    0.0\n1221    0.0\n1222    0.0\n1223    0.0\nName: complex, Length: 1198, dtype: float64", "weight": "None", "message_clsname": "'Pipeline'", "message": "None", "**": "{}"}}