{"duration": 0.20444297790527344, "input_args": {"transformer": "StackingEstimator(estimator=ExtraTreesClassifier(criterion='entropy',\n                                                 max_features=0.6000000000000001,\n                                                 min_samples_leaf=18,\n                                                 min_samples_split=14))", "X": "array([[1.00000000e+00, 1.23208404e-03, 9.98767916e-01, 7.27272727e-01],\n       [1.00000000e+00, 1.23208404e-03, 9.98767916e-01, 1.00000000e+00],\n       [1.00000000e+00, 1.23208404e-03, 9.98767916e-01, 1.00000000e+00],\n       ...,\n       [0.00000000e+00, 1.00000000e+00, 3.09014790e-45, 6.25000000e-02],\n       [0.00000000e+00, 1.00000000e+00, 3.09014790e-45, 7.86290323e-02],\n       [0.00000000e+00, 1.00000000e+00, 3.09014790e-45, 6.25000000e-02]])", "y": "27      1.0\n28      1.0\n29      1.0\n30      1.0\n31      1.0\n       ... \n1492    0.0\n1493    0.0\n1494    0.0\n1495    0.0\n1496    0.0\nName: complex, Length: 1197, dtype: float64", "weight": "None", "message_clsname": "'Pipeline'", "message": "None", "**": "{}"}}